vortex/__init__.py
vortex/config.py
vortex/gloves.py
vortex/proxy.py
vortex/sessions.py
vortex/toolbox.py
vortex/algo/__init__.py
vortex/algo/components.py
vortex/algo/mpitools.py
vortex/algo/serversynctools.py
vortex/algo/mpitools_templates/__init__.py
vortex/algo/mpitools_templates/envelope_wrapper_default.tpl
vortex/algo/mpitools_templates/envelope_wrapper_mpiauto.tpl
vortex/algo/mpitools_templates/wrapstd_wrapper_default.tpl
vortex/data/__init__.py
vortex/data/abstractstores.py
vortex/data/containers.py
vortex/data/contents.py
vortex/data/executables.py
vortex/data/flow.py
vortex/data/geometries.ini
vortex/data/geometries.py
vortex/data/handlers.py
vortex/data/outflow.py
vortex/data/providers.py
vortex/data/resources.py
vortex/data/stores.py
vortex/data/sync_templates/__init__.py
vortex/layout/__init__.py
vortex/layout/contexts.py
vortex/layout/dataflow.py
vortex/layout/monitor.py
vortex/nwp/__init__.py
vortex/nwp/algo/__init__.py
vortex/nwp/algo/assim.py
vortex/nwp/algo/clim.py
vortex/nwp/algo/coupling.py
vortex/nwp/algo/eda.py
vortex/nwp/algo/eps.py
vortex/nwp/algo/forecasts.py
vortex/nwp/algo/fpserver.py
vortex/nwp/algo/ifsnaming.py
vortex/nwp/algo/ifsroot.py
vortex/nwp/algo/monitoring.py
vortex/nwp/algo/mpitools.py
vortex/nwp/algo/odbtools.py
vortex/nwp/algo/oopsroot.py
vortex/nwp/algo/oopstests.py
vortex/nwp/algo/request.py
vortex/nwp/algo/stdpost.py
vortex/nwp/data/__init__.py
vortex/nwp/data/assim.py
vortex/nwp/data/boundaries.py
vortex/nwp/data/climfiles.py
vortex/nwp/data/configfiles.py
vortex/nwp/data/consts.py
vortex/nwp/data/ctpini.py
vortex/nwp/data/diagnostics.py
vortex/nwp/data/eda.py
vortex/nwp/data/eps.py
vortex/nwp/data/executables.py
vortex/nwp/data/fields.py
vortex/nwp/data/gridfiles.py
vortex/nwp/data/logs.py
vortex/nwp/data/modelstates.py
vortex/nwp/data/monitoring.py
vortex/nwp/data/namelists.py
vortex/nwp/data/obs.py
vortex/nwp/data/oopsexec.py
vortex/nwp/data/providers.py
vortex/nwp/data/query.py
vortex/nwp/data/stores.py
vortex_nwp-2.2.0.dist-info/licenses/LICENSE
vortex_nwp-2.2.0.dist-info/METADATA
vortex_nwp-2.2.0.dist-info/WHEEL
vortex_nwp-2.2.0.dist-info/top_level.txt
vortex_nwp-2.2.0.dist-info/RECORD
