Metadata-Version: 2.4
Name: vortex-nwp
Version: 2.2.0
Summary: A Python library to write Numerical Weather Prediction pipelines components
Author-email: The Vortex Team <vortex.support@meteo.fr>
License: CECILL-C
Classifier: Development Status :: 4 - Beta
Classifier: License :: CeCILL-C Free Software License Agreement (CECILL-C)
Requires-Python: >=3.7
License-File: LICENSE
Requires-Dist: bronx
Requires-Dist: footprints
Requires-Dist: taylorism
Requires-Dist: tomli
Requires-Dist: arpifs_listings
Provides-Extra: docs
Requires-Dist: sphinx; extra == "docs"
Requires-Dist: sphinx-book-theme; extra == "docs"
Requires-Dist: sphinx-copybutton; extra == "docs"
Provides-Extra: dev
Requires-Dist: ruff==0.9.1; extra == "dev"
Requires-Dist: pytest; extra == "dev"
Dynamic: license-file
